mlcm/__init__.py
mlcm/mlcm.py
mlcm-0.0.1.dist-info/LICENSE
mlcm-0.0.1.dist-info/METADATA
mlcm-0.0.1.dist-info/WHEEL
mlcm-0.0.1.dist-info/top_level.txt
mlcm-0.0.1.dist-info/RECORD
