Metadata-Version: 2.1
Name: mlcm
Version: 0.0.1
Summary: Multi-Label Confusion Matrix
Home-page: https://github.com/mrh110/mlcm
Author: Mohammadreza Heydarian
Author-email: mrh110@gmail.com
License: UNKNOWN
Project-URL: Lab url, https://biomedic.ai
Platform: UNKNOWN
Classifier: Programming Language :: Python :: 3
Classifier: Operating System :: OS Independent
Requires-Python: >=3.6
License-File: LICENSE
Requires-Dist: numpy
